nepali_grammar_tokenizer-0.1.2.dist-info/licenses/LICENSE
nepali_tokenizer/__init__.py
nepali_tokenizer/cli.py
nepali_tokenizer/rules.py
nepali_tokenizer/tokenizer.py
nepali_grammar_tokenizer-0.1.2.dist-info/METADATA
nepali_grammar_tokenizer-0.1.2.dist-info/WHEEL
nepali_grammar_tokenizer-0.1.2.dist-info/entry_points.txt
nepali_grammar_tokenizer-0.1.2.dist-info/top_level.txt
nepali_grammar_tokenizer-0.1.2.dist-info/RECORD
