Metadata-Version: 2.4
Name: nepali-grammar-tokenizer
Version: 0.1.2
Summary: Deterministic, rule-based Nepali grammar tokenizer
Author: Anil Khatiwada
License-Expression: MIT
Project-URL: Homepage, https://github.com/anilkhatiwada/nepali_tokenizer
Project-URL: Repository, https://github.com/anilkhatiwada/nepali_tokenizer
Project-URL: Issues, https://github.com/anilkhatiwada/nepali_tokenizer/issues
Keywords: nepali,nlp,tokenizer,morphology,devanagari
Classifier: Programming Language :: Python :: 3
Classifier: Programming Language :: Python :: 3 :: Only
Classifier: Programming Language :: Python :: 3.9
Classifier: Programming Language :: Python :: 3.10
Classifier: Programming Language :: Python :: 3.11
Classifier: Programming Language :: Python :: 3.12
Classifier: Natural Language :: Nepali
Classifier: Topic :: Text Processing :: Linguistic
Requires-Python: >=3.9
License-File: LICENSE
Dynamic: license-file
